{
  "scenario_id": "task1_001",
  "task": "task1",
  "diff": "--- a/auth/views.py\n+++ b/auth/views.py\n@@ -15,7 +15,7 @@\n def login(request):\n     username = request.POST.get('username')\n     password = request.POST.get('password')\n-    user = authenticate(username, password)\n+    user = authenticate(username, password, request=request)\n     if user:\n         return redirect('/dashboard')\n     return render(request, 'auth/login.html', {'error': 'Invalid credentials'})",
  "dependency_map": {
    "auth/views.py": ["auth/models.py", "core/middleware.py"],
    "auth/models.py": ["db/connection.py"]
  },
  "file_history": {
    "auth/views.py": {
      "commits_last_30d": 5,
      "last_incident": "2024-08-15",
      "test_coverage": 85
    }
  },
  "available_reviewers": ["alice", "bob", "charlie"],
  "ground_truth": {
    "risk_level": "MEDIUM",
    "blast_radius": [],
    "recommended_reviewer": "alice",
    "merge_decision": "REQUEST_CHANGES"
  }
}
